whodunit
