Metadata-Version: 1.1
Name: whodunit
Version: 0.3
Summary: Identifies owner(s) for module lines in a git repo.
Home-page: https://github.com/pmichali/whodunit
Author: Paul Michali
Author-email: pc@michali.net
License: Apache Software License
Platform: any
Classifier: Development Status :: 3 - Alpha
Classifier: Intended Audience :: Developers
Classifier: Topic :: Software Development :: Build Tools
Classifier: License :: OSI Approved :: Apache Software License
Classifier: Natural Language :: English
Classifier: Operating System :: OS Independent
Classifier: Programming Language :: Python :: 2
Classifier: Programming Language :: Python :: 2.7
Classifier: Programming Language :: Python :: 3
Classifier: Programming Language :: Python :: 3.2
Classifier: Programming Language :: Python :: 3.3
Classifier: Programming Language :: Python :: 3.4
